[{"id":17166,"info":{"name":"上海枫泾天娱影城","price":"24","address":"金山区新泾路300弄35号","tags":["座","退","改签","小吃"]},"distance":"1141.9km"},{"id":41746,"info":{"name":"时代国际影城（金山方圆荟店）","price":"33","address":"金山区枫泾镇方圆荟购物中心西区4楼","tags":["座","退","改签","小吃"]},"distance":"1142.7km"},{"id":41216,"info":{"name":"SFC上影国际影城（爱琴海缤纷里店）","price":"33","address":"金山区枫泾镇乐纷路268号爱琴海·缤纷里北区2F","tags":["座","退","改签","小吃"]},"distance":"1147km"},{"id":37630,"info":{"name":"大光明影城（金山百联店）","price":"33","address":"金山区板桥西路189号3楼","tags":["座","杜比全景声厅","退","改签","小吃"]},"distance":"1151.5km"},{"id":40713,"info":{"name":"UVC影城（金山店）","price":"55","address":"金山区海汇街500号11号楼4楼","tags":["座","退","改签","小吃"]},"distance":"1152.5km"},{"id":13237,"info":{"name":"万达影城（金山万达广场IMAX店）","price":"40","address":"金山区龙皓路1188号万达广场F4层","tags":["座","IMAX厅","RealD厅","4DX厅","4D厅","退","改签","小吃"]},"distance":"1152.5km"},{"id":38381,"info":{"name":"公园影城","price":"33","address":"金山区张堰镇花贤路69号10幢","tags":["座","退","改签","小吃"]},"distance":"1152.9km"},{"id":16119,"info":{"name":"0090激光影城","price":"38","address":"金山区朱泾镇沈浦泾路50号1幢A-01","tags":["座","退","改签","小吃"]},"distance":"1152.9km"},{"id":25276,"info":{"name":"SFC上影竞衡八八影城（金山店）","price":"38","address":"金山区志伟路816弄99号","tags":["座","杜比全景声厅","退","改签"]},"distance":"1157.3km"},{"id":37442,"info":{"name":"中影CMA巨幕影城（松江店）","price":"33","address":"松江区小昆山镇文翔路5388弄1号中惠棠里商业广场四楼","tags":["座","退","改签","小吃"]},"distance":"1161.6km"},{"id":41879,"info":{"name":"大光明影城（名悦广场店）","price":"55","address":"金山区亭林镇林吉路717号4层418室","tags":["座","退","改签","小吃"]},"distance":"1163.4km"},{"id":28670,"info":{"name":"CineMaple红叶巨幕影城","price":"55","address":"松江区飞航广场3楼","tags":["座","杜比全景声厅","退","改签","小吃"]},"distance":"1164.4km"},{"id":27582,"info":{"name":"星逸国际影城（松江店）","price":"45","address":"松江区玉树路2575号2楼201","tags":["座","退","改签","小吃"]},"distance":"1164.5km"},{"id":52,"info":{"name":"左岸国际电影城（松江沃尔玛店）","price":"33","address":"松江区岳阳街道松汇中路568号鹿都沃尔玛广场4楼(近庙前街)","tags":["座","退","改签","小吃"]},"distance":"1165.8km"},{"id":36757,"info":{"name":"上影国际影城（松江平高店）","price":"33","address":"松江区中山中路71号平高世贸中心4楼（第一百货对面近庙前街）","tags":["座","退","改签","小吃"]},"distance":"1166km"},{"id":24337,"info":{"name":"上海市松江区QCC激光影城","price":"32","address":"松江区叶政路487号双高广场3层2区","tags":["座","退","改签","小吃"]},"distance":"1166.3km"},{"id":27409,"info":{"name":"万达影城（青浦万达茂IMAX店）","price":"55","address":"青浦区淀山湖大道1059弄1-45号A区4楼","tags":["座","IMAX厅","RealD厅","儿童厅","退","改签","小吃"]},"distance":"1166.4km"},{"id":41623,"info":{"name":"万渡汇影城（松江云间店）","price":"33","address":"松江区中山街道云间路159号云间新天地4层","tags":["座","退","改签","小吃"]},"distance":"1166.5km"},{"id":17360,"info":{"name":"大光明太禾影城（松江店）","price":"38","address":"松江区岳阳街道九峰路118号平高广场401号","tags":["座","退","改签","小吃"]},"distance":"1166.5km"},{"id":38579,"info":{"name":"春天国际影城（蛙城激光巨幕店）","price":"55","address":"青浦区东渡蛙城3楼（上海市淀山湖大道988弄8号）","tags":["座","退","改签","小吃"]},"distance":"1166.6km"}]